xxe/__init__.py
xxe/cli.py
xxe/core.py
xxe-0.1.6.dist-info/METADATA
xxe-0.1.6.dist-info/WHEEL
xxe-0.1.6.dist-info/entry_points.txt
xxe-0.1.6.dist-info/top_level.txt
xxe-0.1.6.dist-info/RECORD
